five.pt-3.0-py2.7-nspkg.pth
five/pt/__init__.py
five/pt/configure.zcml
five/pt/engine.py
five/pt/expressions.py
five/pt/meta.zcml
five.pt-3.0.dist-info/DESCRIPTION.rst
five.pt-3.0.dist-info/METADATA
five.pt-3.0.dist-info/RECORD
five.pt-3.0.dist-info/WHEEL
five.pt-3.0.dist-info/metadata.json
five.pt-3.0.dist-info/namespace_packages.txt
five.pt-3.0.dist-info/top_level.txt
