Metadata-Version: 1.1
Name: five.pt
Version: 3.0
Summary: DEPRECATED: Five bridges and patches to use Chameleon with Zope.
Home-page: https://github.com/zopefoundation/five.pt
Author: Zope Foundation and Contributors
Author-email: zope-dev@zope.org
License: ZPL
Platform: UNKNOWN
Classifier: Development Status :: 7 - Inactive
Classifier: Framework :: Zope :: 4
Classifier: Programming Language :: Python
Classifier: Programming Language :: Python :: 2.7
Classifier: Programming Language :: Python :: 3.4
Classifier: Programming Language :: Python :: 3.5
Classifier: Programming Language :: Python :: 3.6
Classifier: Topic :: Text Processing :: Markup :: HTML
Classifier: Topic :: Text Processing :: Markup :: XML
